LICENSE
README.md
setup.py
botweb/__init__.py
botweb/decorators.py
botweb/exceptions.py
botweb/web.py
botweb.egg-info/PKG-INFO
botweb.egg-info/SOURCES.txt
botweb.egg-info/dependency_links.txt
botweb.egg-info/requires.txt
botweb.egg-info/top_level.txt